kymata/__init__.py
kymata/data/cbu_specific_files/SSS/ct_sparse_2012.fif
kymata/data/cbu_specific_files/SSS/ct_sparse_2023.fif
kymata/data/cbu_specific_files/SSS/sss_cal_2012.dat
kymata/data/cbu_specific_files/SSS/sss_cal_2023.dat
kymata/data/sensor_locations/CTF-275-channel-name-mapping.yaml
kymata/data/sensor_locations/CTF-275.lout
kymata/data/sensor_locations/CTF-275.lout.LICENSE.txt
kymata/data/sensor_locations/EEG1005-channel-name-mappings.yaml
kymata/data/sensor_locations/EEG1005.lay
kymata/data/sensor_locations/EEG1005.lay.LICENSE.txt
kymata/data/sensor_locations/KIT-AD.lout
kymata/data/sensor_locations/KIT-AD.lout.LICENSE.txt
kymata/data/sensor_locations/Vectorview-all.lout
kymata/data/sensor_locations/Vectorview-all.lout.LICENSE.txt
kymata/dataset_config/dataset3.yaml
kymata/dataset_config/dataset4.1.yaml
kymata/dataset_config/dataset4.yaml
kymata/dataset_config/subject_name_recording_config (template).yaml
kymata/datasets/__init__.py
kymata/datasets/data_root.py
kymata/datasets/fsaverage.py
kymata/datasets/sample.py
kymata/entities/__init__.py
kymata/entities/constants.py
kymata/entities/datatypes.py
kymata/entities/expression.py
kymata/entities/iterables.py
kymata/entities/rudimentary.py
kymata/entities/sparse_data.py
kymata/entities/transform.py
kymata/gridsearch/__init__.py
kymata/gridsearch/plain.py
kymata/invokers/__init__.py
kymata/invokers/invoker_convert_to_bids.py
kymata/invokers/invoker_create_trialwise_data.py
kymata/invokers/invoker_estimate_noise_cov_matrix.py
kymata/invokers/invoker_run_data_cleansing.py
kymata/invokers/invoker_run_hexel_current_estimation.py
kymata/invokers/invoker_run_nkg_plotting.py
kymata/invokers/run_gridsearch.py
kymata/io/__init__.py
kymata/io/atlas.py
kymata/io/bids.py
kymata/io/cli.py
kymata/io/config.py
kymata/io/file.py
kymata/io/json.py
kymata/io/layouts.py
kymata/io/logging.py
kymata/io/matlab.py
kymata/io/nkg.py
kymata/io/nkg_compatibility.py
kymata/io/transform.py
kymata/ippm/__init__.py
kymata/ippm/cluster.py
kymata-1.0.6.dist-info/METADATA
kymata-1.0.6.dist-info/WHEEL
kymata-1.0.6.dist-info/licenses/LICENSE
kymata-1.0.6.dist-info/RECORD
