Metadata-Version: 2.4
Name: kymata
Version: 1.0.6
Summary: Core Kymata codebase, including statistical analysis and plotting tools
License-File: LICENSE
Keywords: neuroscience,neuroimaging
Author: Kymata Research Group
Author-email: acgt2@cam.ac.uk
Requires-Python: >=3.11,<3.12
Classifier: Intended Audience :: Science/Research
Classifier: License :: OSI Approved :: MIT License
Classifier: Natural Language :: English
Classifier: Programming Language :: Python :: 3
Classifier: Programming Language :: Python :: 3.11
Classifier: Topic :: Scientific/Engineering :: Bio-Informatics
Classifier: Topic :: Scientific/Engineering :: Information Analysis
Classifier: Topic :: Scientific/Engineering :: Visualization
Requires-Dist: PyYAML (>=6.0,<7.0)
Requires-Dist: colorama (>=0.4.5,<0.5.0)
Requires-Dist: h5io (>=0.1.9,<0.2.0)
Requires-Dist: jupyter (>=1.1.0,<2.0.0)
Requires-Dist: llvmlite (>=0.41.0,<0.42.0)
Requires-Dist: mat73 (>=0.62,<0.63)
Requires-Dist: matplotlib (>=3.7.1,<4.0.0)
Requires-Dist: mkdocs-material (>=9.5.24,<10.0.0)
Requires-Dist: mkdocstrings[python] (>=0.29.0,<0.30.0)
Requires-Dist: mne (>=1.5.1,<2.0.0)
Requires-Dist: networkx (>=3.4.2,<4.0.0)
Requires-Dist: nibabel (>=5.1.0,<6.0.0)
Requires-Dist: nilearn (>=0.12.1,<0.13.0)
Requires-Dist: pandas (>=2.1.1,<3.0.0)
Requires-Dist: pyqt6 (>=6.6.1,<7.0.0)
Requires-Dist: pyvistaqt (>=0.11.0,<0.12.0)
Requires-Dist: requests (>=2.32.0,<3.0.0)
Requires-Dist: scikit-learn (>=1.3.2,<2.0.0)
Requires-Dist: seaborn (>=0.12.2,<0.13.0)
Requires-Dist: sparse (>=0.14.0,<0.15.0)
Requires-Dist: traitlets (>=5.13.0,<6.0.0)
Requires-Dist: twine (>=5.1.1,<6.0.0)
Requires-Dist: xarray (>=2023.9.0,<2024.0.0)
Project-URL: Documentation, https://kymata-atlas.github.io/kymata-core/
Project-URL: Homepage, https://kymata.org
Project-URL: Repository, https://github.com/kymata-atlas/kymata-core
